mx_stream_core/__init__.py
mx_stream_core/config/__init__.py
mx_stream_core/config/app.py
mx_stream_core/config/delta.py
mx_stream_core/config/event_store.py
mx_stream_core/config/kafka.py
mx_stream_core/config/layer_events.py
mx_stream_core/config/s3.py
mx_stream_core/config/spark.py
mx_stream_core/config/streams.py
mx_stream_core/data_sinks/__init__.py
mx_stream_core/data_sinks/base.py
mx_stream_core/data_sinks/delta.py
mx_stream_core/data_sinks/delta_table.py
mx_stream_core/data_sinks/kafka.py
mx_stream_core/data_sources/__init__.py
mx_stream_core/data_sources/async_query.py
mx_stream_core/data_sources/async_source.py
mx_stream_core/data_sources/base.py
mx_stream_core/data_sources/base_query.py
mx_stream_core/data_sources/delta_table.py
mx_stream_core/data_sources/eventstore.py
mx_stream_core/data_sources/spark_delta.py
mx_stream_core/data_sources/spark_interval_streaming.py
mx_stream_core/data_sources/spark_kafka.py
mx_stream_core/data_sources/pandas/__init__.py
mx_stream_core/data_sources/pandas/update_with_state.py
mx_stream_core/infrastructure/__init__.py
mx_stream_core/infrastructure/delta.py
mx_stream_core/infrastructure/event_store.py
mx_stream_core/infrastructure/kafka.py
mx_stream_core/infrastructure/redis.py
mx_stream_core/infrastructure/spark.py
mx_stream_core/infrastructure/spark_session.py
mx_stream_core/schema/__init__.py
mx_stream_core/schema/streaming_query.py
mx_stream_core/tests/__init__.py
mx_stream_core/tests/mock_data_sink.py
mx_stream_core/tests/mock_data_source.py
mx_stream_core/tests/mock_event_async_data_source.py
mx_stream_core/tests/mock_event_source.py
mx_stream_core/tests/query_listener.py
mx_stream_core/utils/__init__.py
mx_stream_core/utils/cmd.py
mx_stream_core/utils/kafka.py
mx_stream_core/utils/telegram.py
mx_stream_core/validators/__init__.py
mx_stream_core/validators/lakehouse_path_validator.py
mx_stream_core-1.5.11.dist-info/LICENSE.txt
mx_stream_core-1.5.11.dist-info/METADATA
mx_stream_core-1.5.11.dist-info/WHEEL
mx_stream_core-1.5.11.dist-info/top_level.txt
mx_stream_core-1.5.11.dist-info/RECORD
