Metadata-Version: 2.1
Name: mx-stream-core
Version: 1.5.11
Summary: This is package stream core of mindx
Home-page: UNKNOWN
Author: MindX Technology School
Author-email: tech@mindx.com.vn
License: LICENSE.txt
Platform: UNKNOWN
License-File: LICENSE.txt
Requires-Dist: pyspark (==3.5.1)
Requires-Dist: numpy
Requires-Dist: delta-spark (==3.1.0)
Requires-Dist: redis (==5.0.5)
Requires-Dist: pandas (==2.0.3)
Requires-Dist: pyarrow (==17.0.0)
Requires-Dist: esdbclient (==1.0.25)
Requires-Dist: kafka-python (==2.0.2)
